simple_locize/init.py
simple_locize/simple_locize.py
simple_locize-1.0.1.dist-info/METADATA
simple_locize-1.0.1.dist-info/WHEEL
simple_locize-1.0.1.dist-info/top_level.txt
simple_locize-1.0.1.dist-info/RECORD
