Metadata-Version: 2.1
Name: simple-locize
Version: 1.0.1
Summary: A lightweight library for handling translations via the Locize API
Home-page: https://github.com/Maxoplata/simple-locize-py
Author: Maxamilian Demian
Author-email: max@maxdemian.com
License: MIT
Classifier: Programming Language :: Python
Classifier: Operating System :: OS Independent
Classifier: License :: OSI Approved :: MIT License
Classifier: Intended Audience :: Developers
